cooltool_library/__init__.py
cooltool_library/cooltool_library.py
cooltool_library-1.1.2.dist-info/LICENSE.txt
cooltool_library-1.1.2.dist-info/METADATA
cooltool_library-1.1.2.dist-info/WHEEL
cooltool_library-1.1.2.dist-info/top_level.txt
cooltool_library-1.1.2.dist-info/RECORD
