Metadata-Version: 2.1
Name: cooltool-library
Version: 1.1.2
Summary: Simple library with many function to help you with consol project
Author: Quadzeco
Author-email: example@example.com
License: MIT
Classifier: Development Status :: 5 - Production/Stable
Classifier: Intended Audience :: Developers
Classifier: License :: OSI Approved :: MIT License
Classifier: Programming Language :: Python :: 3
License-File: LICENSE.txt
